MANIFEST.in
README.org
setup.py
pyrsp/__init__.py
pyrsp/cortexhwregs.py
pyrsp/elf.py
pyrsp/rsp.py
pyrsp/utils.py
pyrsp.egg-info/PKG-INFO
pyrsp.egg-info/SOURCES.txt
pyrsp.egg-info/dependency_links.txt
pyrsp.egg-info/entry_points.txt
pyrsp.egg-info/requires.txt
pyrsp.egg-info/top_level.txt
test/tests.py