Metadata-Version: 1.1
Name: pyrsp
Version: 0.4
Summary: simple GDB remote serial protocol wrapper
Home-page: https://github.com/stef/pyrsp
Author: Stefan Marsiske
Author-email: s@ctrlc.hu
License: AGPLv3
Keywords: GDB remote debugging JTAG embedded scripting
Platform: UNKNOWN
Classifier: Development Status :: 4 - Beta
Classifier: License :: OSI Approved :: GNU Affero General Public License v3 or later (AGPLv3+)
